sensu_go/__init__.py
sensu_go/errors.py
sensu_go/typing.py
sensu_go/clients/__init__.py
sensu_go/clients/root.py
sensu_go/clients/http/__init__.py
sensu_go/clients/http/api_key.py
sensu_go/clients/http/base.py
sensu_go/clients/http/user_pass.py
sensu_go/clients/resource/__init__.py
sensu_go/clients/resource/base.py
sensu_go/clients/resource/cluster.py
sensu_go/clients/resource/namespaced.py
sensu_go/clients/resource/operator.py
sensu_go/resources/__init__.py
sensu_go/resources/asset.py
sensu_go/resources/base.py
sensu_go/resources/check.py
sensu_go/resources/cluster.py
sensu_go/resources/entity.py
sensu_go/resources/event.py
sensu_go/resources/filter.py
sensu_go/resources/handler.py
sensu_go/resources/hook.py
sensu_go/resources/mutator.py
sensu_go/resources/namespace.py
sensu_go/resources/namespaced.py
sensu_go/resources/secret.py
sensu_go/resources/secrets_provider.py
sensu_go/resources/silence.py
sensu_go/resources/user.py
sensu_go/resources/v1.py
sensu_go/resources/v2.py
sensu_go-0.5.0.dist-info/LICENSE
sensu_go-0.5.0.dist-info/METADATA
sensu_go-0.5.0.dist-info/WHEEL
sensu_go-0.5.0.dist-info/top_level.txt
sensu_go-0.5.0.dist-info/zip-safe
sensu_go-0.5.0.dist-info/RECORD
