Metadata-Version: 2.1
Name: sensu-go
Version: 0.5.0
Summary: Sensu Go Python client
Home-page: https://github.com/xlab-steampunk/sensu-go-python
Author: XLAB Steampunk
Author-email: steampunk@xlab.si
License: MIT
Project-URL: Bug Tracker, https://github.com/xlab-steampunk/sensu-go-python/issues
Project-URL: Release Management, https://github.com/xlab-steampunk/sensu-go-python/releases
Project-URL: Discussions, https://github.com/xlab-steampunk/sensu-go-python/discussions
Project-URL: Source Code, https://github.com/xlab-steampunk/sensu-go-python
Keywords: monitoring
Platform: UNKNOWN
Classifier: Development Status :: 3 - Alpha
Classifier: Environment :: Console
Classifier: Intended Audience :: Developers
Classifier: License :: OSI Approved :: MIT License
Classifier: Operating System :: OS Independent
Classifier: Programming Language :: Python :: 3
Classifier: Programming Language :: Python :: 3.6
Classifier: Programming Language :: Python :: 3.7
Classifier: Programming Language :: Python :: 3.8
Classifier: Programming Language :: Python :: 3.9
Classifier: Topic :: Software Development :: Libraries :: Python Modules
Classifier: Topic :: System :: Monitoring
Requires-Python: >=3.6
Requires-Dist: requests (<3.0)
Provides-Extra: dev
Requires-Dist: black ; extra == 'dev'
Requires-Dist: flake8 ; extra == 'dev'
Requires-Dist: mypy ; extra == 'dev'
Requires-Dist: pytest (<7,>=6) ; extra == 'dev'
Requires-Dist: pytest-mock ; extra == 'dev'
Requires-Dist: requests-mock ; extra == 'dev'
Requires-Dist: wheel ; extra == 'dev'
